LICENSE
README.md
setup.py
bin/paperstack
paperstack/__init__.py
paperstack/__main__.py
paperstack/utility.py
paperstack.egg-info/PKG-INFO
paperstack.egg-info/SOURCES.txt
paperstack.egg-info/dependency_links.txt
paperstack.egg-info/requires.txt
paperstack.egg-info/top_level.txt
paperstack/data/__init__.py
paperstack/data/constants.py
paperstack/data/library.py
paperstack/data/record.py
paperstack/data/scraper.py
paperstack/data/scrapers/__init__.py
paperstack/data/scrapers/ads.py
paperstack/data/scrapers/arxiv.py
paperstack/data/scrapers/mnras.py
paperstack/filesystem/__init__.py
paperstack/filesystem/config.py
paperstack/filesystem/file.py
paperstack/interface/__init__.py
paperstack/interface/app.py
paperstack/interface/details.py
paperstack/interface/keymap.py
paperstack/interface/list.py
paperstack/interface/message.py
paperstack/interface/table.py
paperstack/interface/util.py